kerass/__init__.py
kerasAndMatplotlib-0.1.dist-info/METADATA
kerasAndMatplotlib-0.1.dist-info/WHEEL
kerasAndMatplotlib-0.1.dist-info/top_level.txt
kerasAndMatplotlib-0.1.dist-info/RECORD
