Metadata-Version: 2.1
Name: kerasAndMatplotlib
Version: 0.1
Summary: Keras is an open-source deep learning framework written in Python. It provides a high-level interface for building and training neural networks. Keras was developed with a focus on simplicity and ease of use, allowing researchers and developers to quickly prototype and build deep learning models.
Home-page: UNKNOWN
Author: MrBeast
Author-email: UNKNOWN
License: UNKNOWN
Platform: UNKNOWN
